[
  {
    "Id": "1257ad4f-2779-4d29-952e-437d4174a9bd",
    "FirstName": "Сергiй",
    "LastName": "Косовчич",
    "MiddleName": "Косчич",
    "Address": "м. Київ, вул. Шевченка 123",
    "Phone": "+380505542312"
  },
  {
    "Id": "529d25a1-5181-40fb-9648-10287a9cd102",
    "FirstName": "Михайло",
    "LastName": "Морараш",
    "MiddleName": "Морашович",
    "Address": "с. Буяни, вул. Жукова 45",
    "Phone": "+380504245876"
  },
  {
    "Id": "ac382283-e796-48a9-a18f-65346ea1668e",
    "FirstName": "Андрiй",
    "LastName": "Дробот",
    "MiddleName": "Дробич",
    "Address": "м. Чернiвцi, вул. Унiверситетська 1",
    "Phone": "+380999186399"
  },
  {
    "Id": "d32e3694-8cdd-40f1-88cd-c38817a27c10",
    "FirstName": "Роман",
    "LastName": "Iвасюк",
    "MiddleName": "Iвасич",
    "Address": "м. Кiцмань, вул. Котова 5",
    "Phone": "+38095645115"
  },
  {
    "Id": "8dbe6407-e878-4488-a04e-2e110ea0b31e",
    "FirstName": "Микола",
    "LastName": "Гуцуляк",
    "MiddleName": "Миколайович",
    "Address": "м. Снятин, вул. Польова, 4",
    "Phone": "+380664752131"
  },
  {
    "Id": "0d5416f2-9461-402a-8098-ea6bd526e9c8",
    "FirstName": "Володимир",
    "LastName": "Сухолиткий",
    "MiddleName": "Сухолитич",
    "Address": "м. Харкiв, вул. Хитикая, 88",
    "Phone": "+3809755887799"
  },
  {
    "Id": "355ca277-044f-4c22-b683-79160ebb233c",
    "FirstName": "Андрiй",
    "LastName": "Ляшкевич",
    "MiddleName": "Ляшкович",
    "Address": "м. Черкаси, вул. Кличка, 33",
    "Phone": "+380664512321"
  },
  {
    "Id": "9c4fd46a-cd36-4a0c-8bbf-735795997eb6",
    "FirstName": "Валерiй",
    "LastName": "Кур",
    "MiddleName": "Степанович",
    "Address": "м. Чернiвцi, вул. Унiверситетська 45",
    "Phone": "+380504567898"
  },
  {
    "Id": "c218d299-eec8-49fc-b57d-a31d51c6d4ff",
    "FirstName": "Петро",
    "LastName": "Михайлецький",
    "MiddleName": "Петрович",
    "Address": "м. Чернiвцi, вул. Унiверситетська 22",
    "Phone": "+380504127898"
  },
  {
    "Id": "e4ef75dc-7455-4b3c-b08a-f82b10502e64",
    "FirstName": "Михайло",
    "LastName": "Петришин",
    "MiddleName": "Михайлович",
    "Address": "м. Чернiгiв, вул. Китайська, 88",
    "Phone": "+38096452314"
  }
]